data_ram.v
// ============================================================
//  Data RAM - 256 x 8-bit synchronous
// ============================================================
module data_ram (
    input  wire       clk,
    input  wire       we,
    input  wire [7:0] addr,
    input  wire [7:0] wr_data,
    output reg  [7:0] rd_data
);

    reg [7:0] mem [0:255];
    integer i;

    initial begin
        for (i = 0; i < 256; i = i + 1)
            mem[i] = 8'd0;
        rd_data = 8'd0;
    end

    always @(posedge clk) begin
        if (we)
            mem[addr] <= wr_data;
        rd_data <= mem[addr];
    end

endmodule

alu.v
// ============================================================
//  ALU - 8-bit Arithmetic & Logic Unit
//  Supports: ADD, SUB, AND, OR, XOR, NOT, SHL, SHR
//
//  FIX: 'result' must be a wire, not a reg, because it is
//       driven by a continuous 'assign' statement.
// ============================================================
module alu (
    input  wire [7:0] a,
    input  wire [7:0] b,
    input  wire [2:0] op,
    output wire [7:0] result,      // <-- was 'reg', now 'wire'
    output wire       zero,
    output wire       carry,
    output wire       negative
);

    localparam ADD = 3'd0;
    localparam SUB = 3'd1;
    localparam AND = 3'd2;
    localparam OR  = 3'd3;
    localparam XOR = 3'd4;
    localparam NOT = 3'd5;
    localparam SHL = 3'd6;
    localparam SHR = 3'd7;

    reg [8:0] full_result;   // 9-bit to capture carry out

    always @(*) begin
        case (op)
            ADD: full_result = {1'b0, a} + {1'b0, b};
            SUB: full_result = {1'b0, a} - {1'b0, b};
            AND: full_result = {1'b0, a & b};
            OR:  full_result = {1'b0, a | b};
            XOR: full_result = {1'b0, a ^ b};
            NOT: full_result = {1'b0, ~a};
            SHL: full_result = {a[7], a[6:0], 1'b0};
            SHR: full_result = {a[0], 1'b0, a[7:1]};
            default: full_result = 9'd0;
        endcase
    end

    assign result   = full_result[7:0];
    assign carry    = full_result[8];
    assign zero     = (full_result[7:0] == 8'd0);
    assign negative = full_result[7];

endmodule

register_file.v
// ============================================================
//  Register File - 8 x 8-bit registers (R0-R7)
//  R0 is hardwired to 0. Asynchronous read, synchronous write.
//  Adds dedicated debug read ports for R1/R2/R3.
// ============================================================
module register_file (
    input  wire       clk,
    input  wire       rst,
    input  wire       we,
    input  wire [2:0] rd_addr,
    input  wire [2:0] rs1_addr,
    input  wire [2:0] rs2_addr,
    input  wire [7:0] wr_data,
    output wire [7:0] rs1_data,
    output wire [7:0] rs2_data,
    // Debug taps (do not affect CPU operation)
    output wire [7:0] dbg_r1,
    output wire [7:0] dbg_r2,
    output wire [7:0] dbg_r3
);

    reg [7:0] regs [0:7];
    integer i;

    always @(posedge clk or posedge rst) begin
        if (rst) begin
            for (i = 0; i < 8; i = i + 1)
                regs[i] <= 8'd0;
        end else if (we && rd_addr != 3'd0) begin
            regs[rd_addr] <= wr_data;
        end
    end

    assign rs1_data = (rs1_addr == 3'd0) ? 8'd0 : regs[rs1_addr];
    assign rs2_data = (rs2_addr == 3'd0) ? 8'd0 : regs[rs2_addr];

    assign dbg_r1 = regs[1];
    assign dbg_r2 = regs[2];
    assign dbg_r3 = regs[3];

endmodule

instr_rom.v
// ============================================================
//  Instruction ROM - 256 x 8-bit
//  FIX: 'integer i' moved to module scope. Declaring it inside a
//       named begin/end block within an initial is legal Verilog
//       but Vivado's synthesiser is fussy about it.
//
//  Encoding (2 bytes per instruction):
//    Byte1: [7:5]=opcode  [4:2]=rd  [1]=use_imm  [0]=unused
//    Byte2: LOAD/JMP -> imm8
//           ALU ops  -> [7:5]=rs1  [4:2]=rs2
//           STORE    -> [2:0]=address register
// ============================================================
module instr_rom (
    input  wire [7:0] addr,
    output wire [7:0] data
);

    reg [7:0] rom [0:255];
    integer i;

    initial begin
        for (i = 0; i < 256; i = i + 1)
            rom[i] = 8'b000_000_00;   // default NOP

        rom[0] = 8'b001_001_10;  // LOAD R1, imm
        rom[1] = 8'd10;          //   imm = 10

        rom[2] = 8'b001_010_10;  // LOAD R2, imm
        rom[3] = 8'd20;          //   imm = 20

        rom[4] = 8'b010_011_00;  // ADD  R3, ...
        rom[5] = 8'b001_010_00;  //   rs1=R1, rs2=R2   -> R3 = 30

        rom[6] = 8'b110_011_00;  // STORE R3 -> MEM[...]
        rom[7] = 8'b000_000_00;  //   address register = R0 (=0)

        rom[8] = 8'b111_000_10;  // JMP imm
        rom[9] = 8'd0;           //   target = 0 (loop forever)
    end

    assign data = rom[addr];

endmodule

cpu.v
// ============================================================
//  Top-level CPU: Control Unit + Datapath
//
//  FIXES vs. first version:
//   1. ram_rd_data was a 'reg' driven by a module output -> now wire
//   2. Removed tri-state (8'hZZ) debug output - not synthesisable
//      as internal logic. Debug now comes from register_file taps.
//   3. TIMING BUG: register addresses were latched with <= in the
//      same cycle their data was consumed, so rs1_data/rs2_data
//      were one instruction stale. Addresses are now COMBINATIONAL,
//      so the async-read register file returns valid data in the
//      same cycle. This also let the FSM drop from 4 states to 3.
//
//  FSM: FETCH -> FETCH2 -> EXECUTE -> (back to FETCH)
// ============================================================
module cpu (
    input  wire       clk,
    input  wire       rst,
    input  wire       en,          // clock enable (slow tick for board demo)
    output wire [7:0] dbg_pc,
    output wire [7:0] dbg_reg1,
    output wire [7:0] dbg_reg2,
    output wire [7:0] dbg_reg3
);

    // ---- Opcodes ----
    localparam OP_NOP   = 3'd0;
    localparam OP_LOAD  = 3'd1;
    localparam OP_ADD   = 3'd2;
    localparam OP_SUB   = 3'd3;
    localparam OP_AND   = 3'd4;
    localparam OP_OR    = 3'd5;
    localparam OP_STORE = 3'd6;
    localparam OP_JMP   = 3'd7;

    // ---- ALU ops ----
    localparam ALU_ADD = 3'd0;
    localparam ALU_SUB = 3'd1;
    localparam ALU_AND = 3'd2;
    localparam ALU_OR  = 3'd3;

    // ---- FSM states ----
    localparam S_FETCH  = 2'd0;
    localparam S_FETCH2 = 2'd1;
    localparam S_EXEC   = 2'd2;

    reg [7:0] pc;
    reg [7:0] ir;
    reg [7:0] ir2;
    reg [1:0] state;

    wire [2:0] opcode = ir[7:5];
    wire [2:0] rd     = ir[4:2];

    wire [7:0] rom_data;
    wire [7:0] rs1_data, rs2_data;
    wire [7:0] alu_result;
    wire       alu_zero, alu_carry, alu_neg;
    wire [7:0] ram_rd_data;          // <-- was 'reg', now wire

    // ---- COMBINATIONAL control + address decode ----
    reg  [2:0] rs1_addr, rs2_addr;
    reg  [2:0] alu_op;
    reg  [7:0] wr_data;
    reg        reg_we, ram_we;

    always @(*) begin
        // safe defaults
        rs1_addr = 3'd0;
        rs2_addr = 3'd0;
        alu_op   = ALU_ADD;
        wr_data  = 8'd0;
        reg_we   = 1'b0;
        ram_we   = 1'b0;

        case (opcode)
            OP_LOAD: begin
                wr_data = ir2;
                reg_we  = (state == S_EXEC) && en;
            end
            OP_ADD, OP_SUB, OP_AND, OP_OR: begin
                rs1_addr = ir2[7:5];
                rs2_addr = ir2[4:2];
                case (opcode)
                    OP_ADD: alu_op = ALU_ADD;
                    OP_SUB: alu_op = ALU_SUB;
                    OP_AND: alu_op = ALU_AND;
                    default: alu_op = ALU_OR;
                endcase
                wr_data = alu_result;
                reg_we  = (state == S_EXEC) && en;
            end
            OP_STORE: begin
                rs1_addr = rd;          // value to store
                rs2_addr = ir2[2:0];    // address register
                ram_we   = (state == S_EXEC) && en;
            end
            default: ; // NOP, JMP use defaults
        endcase
    end

    // ---- Submodules ----
    instr_rom rom0 (
        .addr(pc),
        .data(rom_data)
    );

    register_file rf0 (
        .clk     (clk),
        .rst     (rst),
        .we      (reg_we),
        .rd_addr (rd),
        .rs1_addr(rs1_addr),
        .rs2_addr(rs2_addr),
        .wr_data (wr_data),
        .rs1_data(rs1_data),
        .rs2_data(rs2_data),
        .dbg_r1  (dbg_reg1),
        .dbg_r2  (dbg_reg2),
        .dbg_r3  (dbg_reg3)
    );

    alu alu0 (
        .a       (rs1_data),
        .b       (rs2_data),
        .op      (alu_op),
        .result  (alu_result),
        .zero    (alu_zero),
        .carry   (alu_carry),
        .negative(alu_neg)
    );

    data_ram ram0 (
        .clk    (clk),
        .we     (ram_we),
        .addr   (rs2_data),
        .wr_data(rs1_data),
        .rd_data(ram_rd_data)
    );

    assign dbg_pc = pc;

    // ---- Sequential FSM ----
    always @(posedge clk or posedge rst) begin
        if (rst) begin
            pc    <= 8'd0;
            ir    <= 8'd0;
            ir2   <= 8'd0;
            state <= S_FETCH;
        end else if (en) begin
            case (state)
                S_FETCH: begin
                    ir    <= rom_data;
                    pc    <= pc + 8'd1;
                    state <= S_FETCH2;
                end
                S_FETCH2: begin
                    ir2   <= rom_data;
                    pc    <= pc + 8'd1;
                    state <= S_EXEC;
                end
                S_EXEC: begin
                    if (opcode == OP_JMP)
                        pc <= ir2;
                    state <= S_FETCH;
                end
                default: state <= S_FETCH;
            endcase
        end
    end

endmodule

cpu_tb.v
`timescale 1ns/1ps

module cpu_tb;
    reg clk, rst, en;
    wire [7:0] dbg_pc, dbg_r1, dbg_r2, dbg_r3;

    cpu dut (
        .clk(clk), .rst(rst), .en(en),
        .dbg_pc(dbg_pc), .dbg_reg1(dbg_r1),
        .dbg_reg2(dbg_r2), .dbg_reg3(dbg_r3)
    );

    always #5 clk = ~clk;

    integer c;
    initial begin
        $dumpfile("cpu_tb.vcd");
        $dumpvars(0, cpu_tb);

        clk = 0; rst = 1; en = 1; c = 0;
        #20 rst = 0;

        $display("cyc   PC   R1   R2   R3");
        repeat (24) begin
            @(posedge clk);
            #1;
            c = c + 1;
            $display("%3d  %3d  %3d  %3d  %3d", c, dbg_pc, dbg_r1, dbg_r2, dbg_r3);
        end

        $display("");
        if (dbg_r1 == 8'd10 && dbg_r2 == 8'd20 && dbg_r3 == 8'd30)
            $display("PASS: R1=%0d R2=%0d R3=%0d", dbg_r1, dbg_r2, dbg_r3);
        else
            $display("FAIL: R1=%0d R2=%0d R3=%0d (expected 10/20/30)",
                     dbg_r1, dbg_r2, dbg_r3);
        $finish;
    end
endmodule

softcore_CPU/softcore_CPU.sim/sim_1/behav/xsim/cpu_tb.vcd
$date
   Wed Aug  5 02:13:58 2026
$end

$version
  2025.1.0
  $dumpfile ("cpu_tb.vcd") 
$end

$timescale
  1ps
$end

$scope module cpu_tb $end
$var reg 1 ! clk $end
$var reg 1 " rst $end
$var reg 1 # en $end
$var wire 8 $ dbg_pc [7:0] $end
$var wire 8 % dbg_r1 [7:0] $end
$var wire 8 & dbg_r2 [7:0] $end
$var wire 8 ' dbg_r3 [7:0] $end
$var integer 32 ( c [31:0] $end
$scope module dut $end
$var wire 1 ) clk $end
$var wire 1 * rst $end
$var wire 1 + en $end
$var wire 8 $ dbg_pc [7:0] $end
$var wire 8 % dbg_reg1 [7:0] $end
$var wire 8 & dbg_reg2 [7:0] $end
$var wire 8 ' dbg_reg3 [7:0] $end
$var reg 8 , pc [7:0] $end
$var reg 8 - ir [7:0] $end
$var reg 8 . ir2 [7:0] $end
$var reg 2 / state [1:0] $end
$var wire 3 0 opcode [2:0] $end
$var wire 3 1 rd [2:0] $end
$var wire 8 2 rom_data [7:0] $end
$var wire 8 3 rs1_data [7:0] $end
$var wire 8 4 rs2_data [7:0] $end
$var wire 8 5 alu_result [7:0] $end
$var wire 1 6 alu_zero $end
$var wire 1 7 alu_carry $end
$var wire 1 8 alu_neg $end
$var wire 8 9 ram_rd_data [7:0] $end
$var reg 3 : rs1_addr [2:0] $end
$var reg 3 ; rs2_addr [2:0] $end
$var reg 3 < alu_op [2:0] $end
$var reg 8 = wr_data [7:0] $end
$var reg 1 > reg_we $end
$var reg 1 ? ram_we $end
$scope module rom0 $end
$var wire 8 @ addr [7:0] $end
$var wire 8 2 data [7:0] $end
$var integer 32 A i [31:0] $end
$upscope $end
$scope module rf0 $end
$var wire 1 ) clk $end
$var wire 1 * rst $end
$var wire 1 B we $end
$var wire 3 1 rd_addr [2:0] $end
$var wire 3 C rs1_addr [2:0] $end
$var wire 3 D rs2_addr [2:0] $end
$var wire 8 E wr_data [7:0] $end
$var wire 8 3 rs1_data [7:0] $end
$var wire 8 4 rs2_data [7:0] $end
$var wire 8 % dbg_r1 [7:0] $end
$var wire 8 & dbg_r2 [7:0] $end
$var wire 8 ' dbg_r3 [7:0] $end
$var integer 32 F i [31:0] $end
$upscope $end
$scope module alu0 $end
$var wire 8 3 a [7:0] $end
$var wire 8 4 b [7:0] $end
$var wire 3 G op [2:0] $end
$var wire 8 5 result [7:0] $end
$var wire 1 6 zero $end
$var wire 1 7 carry $end
$var wire 1 8 negative $end
$var reg 9 H full_result [8:0] $end
$upscope $end
$scope module ram0 $end
$var wire 1 ) clk $end
$var wire 1 I we $end
$var wire 8 4 addr [7:0] $end
$var wire 8 3 wr_data [7:0] $end
$var reg 8 J rd_data [7:0] $end
$var integer 32 K i [31:0] $end
$upscope $end
$upscope $end
$upscope $end
$enddefinitions $end

#0
$dumpvars
0!
1"
1#
b0 $
b0 %
b0 &
b0 '
b0 (
0)
1*
1+
b0 ,
b0 -
b0 .
b0 /
b0 0
b0 1
b100110 2
b0 3
b0 4
b0 5
16
07
08
b0 9
b0 :
b0 ;
b0 <
b0 =
0>
0?
b0 @
b100000000 A
0B
b0 C
b0 D
b0 E
bx F
b0 G
b0 H
0I
b0 J
b100000000 K
$end

#5000
1!
1)

#10000
0!
0)

#15000
1!
1)

#20000
0!
0"
0)
0*

#25000
1!
b1 $
1)
b1 ,
b100110 -
b1 /
b1 0
b1 1
b1010 2
b1 @

#26000
b1 (

#30000
0!
0)

#35000
1!
b10 $
1)
b10 ,
b1010 .
b10 /
b101010 2
b1010 =
1>
b10 @
1B
b1010 E

#36000
b10 (

#40000
0!
0)

#45000
1!
b1010 %
1)
b0 /
b1010 =
0>
0B

#46000
b11 (

#50000
0!
0)

#55000
1!
b11 $
1)
b11 ,
b101010 -
b1 /
b10 1
b10100 2
b1010 =
b11 @

#56000
b100 (

#60000
0!
0)

#65000
1!
b100 $
1)
b100 ,
b10100 .
b10 /
b1001100 2
b10100 =
1>
b100 @
1B
b10100 E

#66000
b101 (

#70000
0!
0)

#75000
1!
b10100 &
1)
b0 /
b10100 =
0>
0B

#76000
b110 (

#80000
0!
0)

#85000
1!
b101 $
1)
b101 ,
b1001100 -
b1 /
b10 0
b11 1
b101000 2
b101 ;
b0 =
b101 @
b101 D
b0 E

#86000
b111 (

#90000
0!
0)

#95000
1!
b110 $
1)
b110 ,
b101000 .
b10 /
b11001100 2
b1010 3
b10100 4
b11110 5
06
b1 :
b10 ;
b11110 =
1>
b110 @
1B
b1 C
b10 D
b11110 E
b11110 H

#96000
b1000 (

#100000
0!
0)

#105000
1!
b11110 '
1)
b0 /
b1 :
b10 ;
b11110 =
0>
0B

#106000
b1001 (

#110000
0!
0)

#115000
1!
b111 $
1)
b111 ,
b11001100 -
b1 /
b110 0
b0 2
b11110 3
b0 4
b11 :
b0 ;
b0 =
b111 @
b11 C
b0 D
b0 E

#116000
b1010 (

#120000
0!
0)

#125000
1!
b1000 $
1)
b1000 ,
b0 .
b10 /
b11100010 2
b11 :
1?
b1000 @
1I

#126000
b1011 (

#130000
0!
0)

#135000
1!
1)
b0 /
b11 :
0?
0I

#136000
b1100 (

#140000
0!
0)

#145000
1!
b1001 $
1)
b1001 ,
b11100010 -
b1 /
b111 0
b0 1
b0 2
b0 3
b0 5
16
b11110 9
b0 :
b1001 @
b0 C
b0 H
b11110 J

#146000
b1101 (

#150000
0!
0)

#155000
1!
b1010 $
1)
b1010 ,
b10 /
b1010 @

#156000
b1110 (

#160000
0!
0)

#165000
1!
b0 $
1)
b0 ,
b0 /
b100110 2
b0 @

#166000
b1111 (

#170000
0!
0)

#175000
1!
b1 $
1)
b1 ,
b100110 -
b1 /
b1 0
b1 1
b1010 2
b1 @

#176000
b10000 (

#180000
0!
0)

#185000
1!
b10 $
1)
b10 ,
b1010 .
b10 /
b101010 2
b1010 =
1>
b10 @
1B
b1010 E

#186000
b10001 (

#190000
0!
0)

#195000
1!
1)
b0 /
b1010 =
0>
0B

#196000
b10010 (

#200000
0!
0)

#205000
1!
b11 $
1)
b11 ,
b101010 -
b1 /
b10 1
b10100 2
b1010 =
b11 @

#206000
b10011 (

#210000
0!
0)

#215000
1!
b100 $
1)
b100 ,
b10100 .
b10 /
b1001100 2
b10100 =
1>
b100 @
1B
b10100 E

#216000
b10100 (

#220000
0!
0)

#225000
1!
1)
b0 /
b10100 =
0>
0B

#226000
b10101 (

#230000
0!
0)

#235000
1!
b101 $
1)
b101 ,
b1001100 -
b1 /
b10 0
b11 1
b101000 2
b101 ;
b0 =
b101 @
b101 D
b0 E

#236000
b10110 (

#240000
0!
0)

#245000
1!
b110 $
1)
b110 ,
b101000 .
b10 /
b11001100 2
b1010 3
b10100 4
b11110 5
06
b1 :
b10 ;
b11110 =
1>
b110 @
1B
b1 C
b10 D
b11110 E
b11110 H

#246000
b10111 (

#250000
0!
0)

#255000
1!
1)
b0 /
b0 9
b1 :
b10 ;
b11110 =
0>
0B
b0 J

#256000
b11000 (
